meteorologicalData/__init__.py
meteorologicalData/main.py
meteorologicalData-0.1.2.dist-info/LICENSE
meteorologicalData-0.1.2.dist-info/METADATA
meteorologicalData-0.1.2.dist-info/WHEEL
meteorologicalData-0.1.2.dist-info/top_level.txt
meteorologicalData-0.1.2.dist-info/RECORD
