Metadata-Version: 2.1
Name: meteorologicalData
Version: 0.1.2
Summary: Um simples pacote para retornar ou visualizar dados meteorológicos de uma determinada cidade
Author: David Moura, Enzo Sá
Author-email: davidmoura0102@gmail.com, enzosa90@gmail.com
License: MIT License
Classifier: Programming Language :: Python :: 3
Requires-Python: >=3.8
License-File: LICENSE
Requires-Dist: folium
Requires-Dist: PyQt5
Requires-Dist: requests
